{"sections":[],"topicSections":[{"title":"Classes","identifiers":["doc:\/\/com.mapbox.navigation\/documentation\/MapboxDirections\/DirectionsOptions","doc:\/\/com.mapbox.navigation\/documentation\/MapboxDirections\/Isochrones","doc:\/\/com.mapbox.navigation\/documentation\/MapboxDirections\/MatchOptions","doc:\/\/com.mapbox.navigation\/documentation\/MapboxDirections\/Matrix","doc:\/\/com.mapbox.navigation\/documentation\/MapboxDirections\/MatrixOptions","doc:\/\/com.mapbox.navigation\/documentation\/MapboxDirections\/RouteOptions"]},{"title":"Protocols","identifiers":["doc:\/\/com.mapbox.navigation\/documentation\/MapboxDirections\/CustomValueOptionSet","doc:\/\/com.mapbox.navigation\/documentation\/MapboxDirections\/DirectionsResult","doc:\/\/com.mapbox.navigation\/documentation\/MapboxDirections\/ForeignMemberContainerClass","doc:\/\/com.mapbox.navigation\/documentation\/MapboxDirections\/OfflineDirectionsProtocol","doc:\/\/com.mapbox.navigation\/documentation\/MapboxDirections\/RouteLegRefreshSource","doc:\/\/com.mapbox.navigation\/documentation\/MapboxDirections\/RouteRefreshSource"]},{"identifiers":["doc:\/\/com.mapbox.navigation\/documentation\/MapboxDirections\/AdministrativeRegion","doc:\/\/com.mapbox.navigation\/documentation\/MapboxDirections\/Amenity","doc:\/\/com.mapbox.navigation\/documentation\/MapboxDirections\/AttributeOptions","doc:\/\/com.mapbox.navigation\/documentation\/MapboxDirections\/BlockedLanes","doc:\/\/com.mapbox.navigation\/documentation\/MapboxDirections\/Credentials","doc:\/\/com.mapbox.navigation\/documentation\/MapboxDirections\/DirectionsCodingKey","doc:\/\/com.mapbox.navigation\/documentation\/MapboxDirections\/DirectionsPriority","doc:\/\/com.mapbox.navigation\/documentation\/MapboxDirections\/GuidanceViewImageRepresentation","doc:\/\/com.mapbox.navigation\/documentation\/MapboxDirections\/Incident","doc:\/\/com.mapbox.navigation\/documentation\/MapboxDirections\/Interchange","doc:\/\/com.mapbox.navigation\/documentation\/MapboxDirections\/Intersection","doc:\/\/com.mapbox.navigation\/documentation\/MapboxDirections\/IsochroneOptions","doc:\/\/com.mapbox.navigation\/documentation\/MapboxDirections\/Junction","doc:\/\/com.mapbox.navigation\/documentation\/MapboxDirections\/LaneIndication","doc:\/\/com.mapbox.navigation\/documentation\/MapboxDirections\/MapMatchingResponse","doc:\/\/com.mapbox.navigation\/documentation\/MapboxDirections\/Match","doc:\/\/com.mapbox.navigation\/documentation\/MapboxDirections\/MatrixResponse","doc:\/\/com.mapbox.navigation\/documentation\/MapboxDirections\/Polyline","doc:\/\/com.mapbox.navigation\/documentation\/MapboxDirections\/ProfileIdentifier","doc:\/\/com.mapbox.navigation\/documentation\/MapboxDirections\/RefreshedRoute","doc:\/\/com.mapbox.navigation\/documentation\/MapboxDirections\/RefreshedRouteLeg","doc:\/\/com.mapbox.navigation\/documentation\/MapboxDirections\/RestStop","doc:\/\/com.mapbox.navigation\/documentation\/MapboxDirections\/RoadClassExclusionViolation","doc:\/\/com.mapbox.navigation\/documentation\/MapboxDirections\/RoadClasses","doc:\/\/com.mapbox.navigation\/documentation\/MapboxDirections\/Route","doc:\/\/com.mapbox.navigation\/documentation\/MapboxDirections\/RouteLeg","doc:\/\/com.mapbox.navigation\/documentation\/MapboxDirections\/RouteRefreshResponse","doc:\/\/com.mapbox.navigation\/documentation\/MapboxDirections\/RouteResponse","doc:\/\/com.mapbox.navigation\/documentation\/MapboxDirections\/RouteStep","doc:\/\/com.mapbox.navigation\/documentation\/MapboxDirections\/SilentWaypoint","doc:\/\/com.mapbox.navigation\/documentation\/MapboxDirections\/SpokenInstruction","doc:\/\/com.mapbox.navigation\/documentation\/MapboxDirections\/TollCategory","doc:\/\/com.mapbox.navigation\/documentation\/MapboxDirections\/TollCollection","doc:\/\/com.mapbox.navigation\/documentation\/MapboxDirections\/TollPaymentMethod","doc:\/\/com.mapbox.navigation\/documentation\/MapboxDirections\/TollPrice","doc:\/\/com.mapbox.navigation\/documentation\/MapboxDirections\/VisualInstruction","doc:\/\/com.mapbox.navigation\/documentation\/MapboxDirections\/VisualInstructionBanner","doc:\/\/com.mapbox.navigation\/documentation\/MapboxDirections\/Waypoint"],"title":"Structures"},{"identifiers":["doc:\/\/com.mapbox.navigation\/documentation\/MapboxDirections\/MBDirectionsErrorDomain"],"title":"Variables"},{"title":"Functions","identifiers":["doc:\/\/com.mapbox.navigation\/documentation\/MapboxDirections\/decodeLevels(_:)","doc:\/\/com.mapbox.navigation\/documentation\/MapboxDirections\/decodePolyline(_:precision:)-1gxs5","doc:\/\/com.mapbox.navigation\/documentation\/MapboxDirections\/decodePolyline(_:precision:)-2ues4","doc:\/\/com.mapbox.navigation\/documentation\/MapboxDirections\/encodeCoordinates(_:precision:)","doc:\/\/com.mapbox.navigation\/documentation\/MapboxDirections\/encodeLevels(_:)","doc:\/\/com.mapbox.navigation\/documentation\/MapboxDirections\/encodeLocations(_:precision:)"]},{"identifiers":["doc:\/\/com.mapbox.navigation\/documentation\/MapboxDirections\/DirectionsCredentials","doc:\/\/com.mapbox.navigation\/documentation\/MapboxDirections\/DirectionsProfileIdentifier","doc:\/\/com.mapbox.navigation\/documentation\/MapboxDirections\/LocationAccuracy","doc:\/\/com.mapbox.navigation\/documentation\/MapboxDirections\/LocationCoordinate2D","doc:\/\/com.mapbox.navigation\/documentation\/MapboxDirections\/LocationSpeed","doc:\/\/com.mapbox.navigation\/documentation\/MapboxDirections\/MBDirectionsPriority","doc:\/\/com.mapbox.navigation\/documentation\/MapboxDirections\/MBDirectionsProfileIdentifier","doc:\/\/com.mapbox.navigation\/documentation\/MapboxDirections\/NumericCongestionLevel","doc:\/\/com.mapbox.navigation\/documentation\/MapboxDirections\/OfflineDownloaderCompletionHandler","doc:\/\/com.mapbox.navigation\/documentation\/MapboxDirections\/OfflineDownloaderProgressHandler","doc:\/\/com.mapbox.navigation\/documentation\/MapboxDirections\/OfflineVersion","doc:\/\/com.mapbox.navigation\/documentation\/MapboxDirections\/OfflineVersionsHandler","doc:\/\/com.mapbox.navigation\/documentation\/MapboxDirections\/Scale"],"title":"Type Aliases"},{"identifiers":["doc:\/\/com.mapbox.navigation\/documentation\/MapboxDirections\/AmenityType","doc:\/\/com.mapbox.navigation\/documentation\/MapboxDirections\/CongestionLevel","doc:\/\/com.mapbox.navigation\/documentation\/MapboxDirections\/CustomOptionComparisonPolicy","doc:\/\/com.mapbox.navigation\/documentation\/MapboxDirections\/DirectionsCodingError","doc:\/\/com.mapbox.navigation\/documentation\/MapboxDirections\/DirectionsError","doc:\/\/com.mapbox.navigation\/documentation\/MapboxDirections\/DirectionsResultCodingKeys","doc:\/\/com.mapbox.navigation\/documentation\/MapboxDirections\/DrivingSide","doc:\/\/com.mapbox.navigation\/documentation\/MapboxDirections\/GeometryError","doc:\/\/com.mapbox.navigation\/documentation\/MapboxDirections\/IsochroneError","doc:\/\/com.mapbox.navigation\/documentation\/MapboxDirections\/ManeuverDirection","doc:\/\/com.mapbox.navigation\/documentation\/MapboxDirections\/ManeuverType","doc:\/\/com.mapbox.navigation\/documentation\/MapboxDirections\/MapboxStreetsRoadClass","doc:\/\/com.mapbox.navigation\/documentation\/MapboxDirections\/MatrixError","doc:\/\/com.mapbox.navigation\/documentation\/MapboxDirections\/MeasurementSystem","doc:\/\/com.mapbox.navigation\/documentation\/MapboxDirections\/ResponseOptions","doc:\/\/com.mapbox.navigation\/documentation\/MapboxDirections\/RouteShapeFormat","doc:\/\/com.mapbox.navigation\/documentation\/MapboxDirections\/RouteShapeResolution","doc:\/\/com.mapbox.navigation\/documentation\/MapboxDirections\/SignStandard","doc:\/\/com.mapbox.navigation\/documentation\/MapboxDirections\/TrafficTendency","doc:\/\/com.mapbox.navigation\/documentation\/MapboxDirections\/TransportType","doc:\/\/com.mapbox.navigation\/documentation\/MapboxDirections\/Weight"],"title":"Enumerations"},{"title":"Extended Modules","identifiers":["doc:\/\/com.mapbox.navigation\/documentation\/MapboxDirections\/Swift","doc:\/\/com.mapbox.navigation\/documentation\/MapboxDirections\/Turf"]}],"identifier":{"url":"doc:\/\/com.mapbox.navigation\/documentation\/MapboxDirections","interfaceLanguage":"swift"},"schemaVersion":{"minor":3,"major":0,"patch":0},"metadata":{"symbolKind":"module","roleHeading":"Framework","role":"collection","modules":[{"name":"MapboxDirections"}],"title":"MapboxDirections","externalID":"MapboxDirections"},"kind":"symbol","hierarchy":{"paths":[[]]},"abstract":[{"type":"text","text":"Quickly get driving, cycling, or walking directions, whether the trip is nonstop or it has multiple stops."}],"primaryContentSections":[{"content":[{"level":2,"text":"Overview","anchor":"Overview","type":"heading"},{"type":"paragraph","inlineContent":[{"text":"Provides basic models for ","type":"text"},{"type":"reference","identifier":"https:\/\/docs.mapbox.com\/api\/navigation\/directions\/","isActive":true},{"type":"text","text":", "},{"identifier":"https:\/\/docs.mapbox.com\/api\/navigation\/map-matching\/","isActive":true,"type":"reference"},{"text":", and ","type":"text"},{"type":"reference","identifier":"https:\/\/docs.mapbox.com\/api\/navigation\/matrix\/","isActive":true},{"type":"text","text":"."}]}],"kind":"content"}],"variants":[{"paths":["\/documentation\/mapboxdirections"],"traits":[{"interfaceLanguage":"swift"}]}],"references":{"doc://com.mapbox.navigation/documentation/MapboxDirections/RouteStep":{"fragments":[{"kind":"keyword","text":"struct"},{"text":" ","kind":"text"},{"kind":"identifier","text":"RouteStep"}],"identifier":"doc:\/\/com.mapbox.navigation\/documentation\/MapboxDirections\/RouteStep","navigatorTitle":[{"text":"RouteStep","kind":"identifier"}],"title":"RouteStep","type":"topic","role":"symbol","kind":"symbol","url":"\/documentation\/mapboxdirections\/routestep","abstract":[{"text":"A ","type":"text"},{"identifier":"doc:\/\/com.mapbox.navigation\/documentation\/MapboxDirections\/RouteStep","type":"reference","isActive":true},{"text":" object represents a single distinct maneuver along a route and the approach to the next maneuver.","type":"text"},{"text":" ","type":"text"},{"text":"The route step object corresponds to a single instruction the user must follow to complete a portion of the route.","type":"text"},{"type":"text","text":" "},{"text":"For example, a step might require the user to turn then follow a road.","type":"text"}]},"doc://com.mapbox.navigation/documentation/MapboxDirections":{"kind":"symbol","identifier":"doc:\/\/com.mapbox.navigation\/documentation\/MapboxDirections","abstract":[{"type":"text","text":"Quickly get driving, cycling, or walking directions, whether the trip is nonstop or it has multiple stops."}],"title":"MapboxDirections","type":"topic","url":"\/documentation\/mapboxdirections","role":"collection"},"doc://com.mapbox.navigation/documentation/MapboxDirections/MBDirectionsErrorDomain":{"type":"topic","title":"MBDirectionsErrorDomain","identifier":"doc:\/\/com.mapbox.navigation\/documentation\/MapboxDirections\/MBDirectionsErrorDomain","url":"\/documentation\/mapboxdirections\/mbdirectionserrordomain","kind":"symbol","role":"symbol","abstract":[{"type":"text","text":"Indicates that an error occurred in MapboxDirections."}],"fragments":[{"text":"let","kind":"keyword"},{"text":" ","kind":"text"},{"text":"MBDirectionsErrorDomain","kind":"identifier"},{"text":": ","kind":"text"},{"text":"String","preciseIdentifier":"s:SS","kind":"typeIdentifier"}]},"doc://com.mapbox.navigation/documentation/MapboxDirections/Turf":{"type":"topic","url":"\/documentation\/mapboxdirections\/turf","identifier":"doc:\/\/com.mapbox.navigation\/documentation\/MapboxDirections\/Turf","abstract":[],"kind":"symbol","title":"Turf","role":"collection"},"doc://com.mapbox.navigation/documentation/MapboxDirections/GuidanceViewImageRepresentation":{"identifier":"doc:\/\/com.mapbox.navigation\/documentation\/MapboxDirections\/GuidanceViewImageRepresentation","title":"GuidanceViewImageRepresentation","type":"topic","navigatorTitle":[{"text":"GuidanceViewImageRepresentation","kind":"identifier"}],"url":"\/documentation\/mapboxdirections\/guidanceviewimagerepresentation","kind":"symbol","role":"symbol","abstract":[{"text":"A guidance view image representation of a visual instruction component.","type":"text"}],"fragments":[{"text":"struct","kind":"keyword"},{"text":" ","kind":"text"},{"text":"GuidanceViewImageRepresentation","kind":"identifier"}]},"doc://com.mapbox.navigation/documentation/MapboxDirections/VisualInstruction":{"navigatorTitle":[{"kind":"identifier","text":"VisualInstruction"}],"kind":"symbol","abstract":[{"type":"text","text":"The contents of a banner that should be displayed as added visual guidance for a route. The banner instructions are"},{"type":"text","text":" "},{"type":"text","text":"children of the steps during which they should be displayed, but they refer to the maneuver in the following step."}],"identifier":"doc:\/\/com.mapbox.navigation\/documentation\/MapboxDirections\/VisualInstruction","fragments":[{"kind":"keyword","text":"struct"},{"text":" ","kind":"text"},{"text":"VisualInstruction","kind":"identifier"}],"title":"VisualInstruction","type":"topic","url":"\/documentation\/mapboxdirections\/visualinstruction","role":"symbol"},"doc://com.mapbox.navigation/documentation/MapboxDirections/MapboxStreetsRoadClass":{"navigatorTitle":[{"kind":"identifier","text":"MapboxStreetsRoadClass"}],"title":"MapboxStreetsRoadClass","kind":"symbol","fragments":[{"kind":"keyword","text":"enum"},{"kind":"text","text":" "},{"kind":"identifier","text":"MapboxStreetsRoadClass"}],"type":"topic","abstract":[{"text":"A road classification according to the ","type":"text"},{"identifier":"https:\/\/docs.mapbox.com\/vector-tiles\/reference\/mapbox-streets-v8\/#road","type":"reference","isActive":true},{"type":"text","text":" , version 8."}],"identifier":"doc:\/\/com.mapbox.navigation\/documentation\/MapboxDirections\/MapboxStreetsRoadClass","url":"\/documentation\/mapboxdirections\/mapboxstreetsroadclass","role":"symbol"},"doc://com.mapbox.navigation/documentation/MapboxDirections/RouteLeg":{"identifier":"doc:\/\/com.mapbox.navigation\/documentation\/MapboxDirections\/RouteLeg","kind":"symbol","navigatorTitle":[{"text":"RouteLeg","kind":"identifier"}],"title":"RouteLeg","abstract":[{"type":"text","text":"A "},{"isActive":true,"identifier":"doc:\/\/com.mapbox.navigation\/documentation\/MapboxDirections\/RouteLeg","type":"reference"},{"type":"text","text":" object defines a single leg of a route between two waypoints. If the overall route has only two"},{"type":"text","text":" "},{"text":"waypoints, it has a single ","type":"text"},{"identifier":"doc:\/\/com.mapbox.navigation\/documentation\/MapboxDirections\/RouteLeg","type":"reference","isActive":true},{"type":"text","text":" object that covers the entire route. The route leg object includes"},{"type":"text","text":" "},{"text":"information about the leg, such as its name, distance, and expected travel time. Depending on the criteria used to","type":"text"},{"text":" ","type":"text"},{"type":"text","text":"calculate the route, the route leg object may also include detailed turn-by-turn instructions."}],"type":"topic","role":"symbol","fragments":[{"text":"struct","kind":"keyword"},{"text":" ","kind":"text"},{"kind":"identifier","text":"RouteLeg"}],"url":"\/documentation\/mapboxdirections\/routeleg"},"doc://com.mapbox.navigation/documentation/MapboxDirections/LocationCoordinate2D":{"kind":"symbol","identifier":"doc:\/\/com.mapbox.navigation\/documentation\/MapboxDirections\/LocationCoordinate2D","role":"symbol","type":"topic","abstract":[],"fragments":[{"kind":"keyword","text":"typealias"},{"kind":"text","text":" "},{"text":"LocationCoordinate2D","kind":"identifier"}],"navigatorTitle":[{"kind":"identifier","text":"LocationCoordinate2D"}],"url":"\/documentation\/mapboxdirections\/locationcoordinate2d","title":"LocationCoordinate2D"},"doc://com.mapbox.navigation/documentation/MapboxDirections/RefreshedRouteLeg":{"navigatorTitle":[{"text":"RefreshedRouteLeg","kind":"identifier"}],"kind":"symbol","abstract":[{"text":"A skeletal route leg containing only the information about the route leg that has been refreshed.","type":"text"}],"identifier":"doc:\/\/com.mapbox.navigation\/documentation\/MapboxDirections\/RefreshedRouteLeg","fragments":[{"text":"struct","kind":"keyword"},{"text":" ","kind":"text"},{"text":"RefreshedRouteLeg","kind":"identifier"}],"url":"\/documentation\/mapboxdirections\/refreshedrouteleg","title":"RefreshedRouteLeg","type":"topic","role":"symbol"},"doc://com.mapbox.navigation/documentation/MapboxDirections/RoadClasses":{"abstract":[{"text":"Option set that contains attributes of a road segment.","type":"text"}],"identifier":"doc:\/\/com.mapbox.navigation\/documentation\/MapboxDirections\/RoadClasses","fragments":[{"text":"struct","kind":"keyword"},{"kind":"text","text":" "},{"kind":"identifier","text":"RoadClasses"}],"role":"symbol","url":"\/documentation\/mapboxdirections\/roadclasses","kind":"symbol","title":"RoadClasses","navigatorTitle":[{"text":"RoadClasses","kind":"identifier"}],"type":"topic"},"doc://com.mapbox.navigation/documentation/MapboxDirections/MeasurementSystem":{"fragments":[{"kind":"keyword","text":"enum"},{"kind":"text","text":" "},{"kind":"identifier","text":"MeasurementSystem"}],"role":"symbol","identifier":"doc:\/\/com.mapbox.navigation\/documentation\/MapboxDirections\/MeasurementSystem","title":"MeasurementSystem","type":"topic","navigatorTitle":[{"text":"MeasurementSystem","kind":"identifier"}],"url":"\/documentation\/mapboxdirections\/measurementsystem","abstract":[{"type":"text","text":"A system of units of measuring distances and other quantities."}],"kind":"symbol"},"doc://com.mapbox.navigation/documentation/MapboxDirections/IsochroneError":{"type":"topic","title":"IsochroneError","identifier":"doc:\/\/com.mapbox.navigation\/documentation\/MapboxDirections\/IsochroneError","navigatorTitle":[{"text":"IsochroneError","kind":"identifier"}],"url":"\/documentation\/mapboxdirections\/isochroneerror","kind":"symbol","role":"symbol","abstract":[{"type":"text","text":"An error that occurs when calculating isochrone contours."}],"fragments":[{"text":"enum","kind":"keyword"},{"text":" ","kind":"text"},{"text":"IsochroneError","kind":"identifier"}]},"doc://com.mapbox.navigation/documentation/MapboxDirections/SpokenInstruction":{"identifier":"doc:\/\/com.mapbox.navigation\/documentation\/MapboxDirections\/SpokenInstruction","abstract":[{"type":"text","text":"An instruction about an upcoming "},{"type":"reference","identifier":"doc:\/\/com.mapbox.navigation\/documentation\/MapboxDirections\/RouteStep","isActive":true},{"text":"’s maneuver, optimized for speech synthesis.","type":"text"}],"fragments":[{"text":"struct","kind":"keyword"},{"kind":"text","text":" "},{"kind":"identifier","text":"SpokenInstruction"}],"role":"symbol","title":"SpokenInstruction","type":"topic","kind":"symbol","url":"\/documentation\/mapboxdirections\/spokeninstruction","navigatorTitle":[{"kind":"identifier","text":"SpokenInstruction"}]},"doc://com.mapbox.navigation/documentation/MapboxDirections/TollPaymentMethod":{"type":"topic","title":"TollPaymentMethod","fragments":[{"kind":"keyword","text":"struct"},{"text":" ","kind":"text"},{"text":"TollPaymentMethod","kind":"identifier"}],"navigatorTitle":[{"kind":"identifier","text":"TollPaymentMethod"}],"identifier":"doc:\/\/com.mapbox.navigation\/documentation\/MapboxDirections\/TollPaymentMethod","abstract":[{"type":"text","text":"Information about toll payment method."}],"role":"symbol","kind":"symbol","url":"\/documentation\/mapboxdirections\/tollpaymentmethod"},"doc://com.mapbox.navigation/documentation/MapboxDirections/SilentWaypoint":{"role":"symbol","url":"\/documentation\/mapboxdirections\/silentwaypoint","kind":"symbol","identifier":"doc:\/\/com.mapbox.navigation\/documentation\/MapboxDirections\/SilentWaypoint","navigatorTitle":[{"text":"SilentWaypoint","kind":"identifier"}],"type":"topic","title":"SilentWaypoint","fragments":[{"text":"struct","kind":"keyword"},{"kind":"text","text":" "},{"kind":"identifier","text":"SilentWaypoint"}],"abstract":[{"text":"Represents a silent waypoint along the ","type":"text"},{"type":"reference","isActive":true,"identifier":"doc:\/\/com.mapbox.navigation\/documentation\/MapboxDirections\/RouteLeg"},{"type":"text","text":"."}]},"doc://com.mapbox.navigation/documentation/MapboxDirections/RouteRefreshSource":{"identifier":"doc:\/\/com.mapbox.navigation\/documentation\/MapboxDirections\/RouteRefreshSource","title":"RouteRefreshSource","type":"topic","navigatorTitle":[{"text":"RouteRefreshSource","kind":"identifier"}],"url":"\/documentation\/mapboxdirections\/routerefreshsource","kind":"symbol","role":"symbol","abstract":[{"text":"A skeletal route containing infromation to refresh ","type":"text"},{"type":"reference","identifier":"doc:\/\/com.mapbox.navigation\/documentation\/MapboxDirections\/Route","isActive":true},{"type":"text","text":" object attributes."}],"fragments":[{"text":"protocol","kind":"keyword"},{"text":" ","kind":"text"},{"kind":"identifier","text":"RouteRefreshSource"}]},"doc://com.mapbox.navigation/documentation/MapboxDirections/OfflineVersion":{"role":"symbol","url":"\/documentation\/mapboxdirections\/offlineversion","identifier":"doc:\/\/com.mapbox.navigation\/documentation\/MapboxDirections\/OfflineVersion","type":"topic","abstract":[],"navigatorTitle":[{"text":"OfflineVersion","kind":"identifier"}],"fragments":[{"text":"typealias","kind":"keyword"},{"kind":"text","text":" "},{"text":"OfflineVersion","kind":"identifier"}],"title":"OfflineVersion","kind":"symbol"},"doc://com.mapbox.navigation/documentation/MapboxDirections/LocationAccuracy":{"type":"topic","title":"LocationAccuracy","identifier":"doc:\/\/com.mapbox.navigation\/documentation\/MapboxDirections\/LocationAccuracy","navigatorTitle":[{"text":"LocationAccuracy","kind":"identifier"}],"url":"\/documentation\/mapboxdirections\/locationaccuracy","kind":"symbol","role":"symbol","abstract":[{"type":"text","text":"The accuracy of a geographical coordinate."}],"fragments":[{"text":"typealias","kind":"keyword"},{"text":" ","kind":"text"},{"text":"LocationAccuracy","kind":"identifier"}]},"https://docs.mapbox.com/api/navigation/directions/":{"titleInlineContent":[{"type":"text","text":"Mapbox Directions API"}],"url":"https:\/\/docs.mapbox.com\/api\/navigation\/directions\/","title":"Mapbox Directions API","identifier":"https:\/\/docs.mapbox.com\/api\/navigation\/directions\/","type":"link"},"doc://com.mapbox.navigation/documentation/MapboxDirections/RouteShapeFormat":{"role":"symbol","type":"topic","kind":"symbol","fragments":[{"text":"enum","kind":"keyword"},{"text":" ","kind":"text"},{"kind":"identifier","text":"RouteShapeFormat"}],"abstract":[{"type":"text","text":"A "},{"identifier":"doc:\/\/com.mapbox.navigation\/documentation\/MapboxDirections\/RouteShapeFormat","isActive":true,"type":"reference"},{"text":" indicates the format of a route or match shape in the raw HTTP response.","type":"text"}],"title":"RouteShapeFormat","navigatorTitle":[{"text":"RouteShapeFormat","kind":"identifier"}],"url":"\/documentation\/mapboxdirections\/routeshapeformat","identifier":"doc:\/\/com.mapbox.navigation\/documentation\/MapboxDirections\/RouteShapeFormat"},"doc://com.mapbox.navigation/documentation/MapboxDirections/Incident":{"kind":"symbol","fragments":[{"kind":"keyword","text":"struct"},{"kind":"text","text":" "},{"kind":"identifier","text":"Incident"}],"url":"\/documentation\/mapboxdirections\/incident","navigatorTitle":[{"text":"Incident","kind":"identifier"}],"type":"topic","role":"symbol","abstract":[{"code":"Incident","type":"codeVoice"},{"text":" describes any corresponding event, used for annotating the route.","type":"text"}],"title":"Incident","identifier":"doc:\/\/com.mapbox.navigation\/documentation\/MapboxDirections\/Incident"},"doc://com.mapbox.navigation/documentation/MapboxDirections/MatrixResponse":{"navigatorTitle":[{"kind":"identifier","text":"MatrixResponse"}],"fragments":[{"text":"struct","kind":"keyword"},{"kind":"text","text":" "},{"kind":"identifier","text":"MatrixResponse"}],"title":"MatrixResponse","abstract":[],"kind":"symbol","identifier":"doc:\/\/com.mapbox.navigation\/documentation\/MapboxDirections\/MatrixResponse","role":"symbol","type":"topic","url":"\/documentation\/mapboxdirections\/matrixresponse"},"doc://com.mapbox.navigation/documentation/MapboxDirections/RoadClassExclusionViolation":{"abstract":[{"text":"Exact ","type":"text"},{"isActive":true,"identifier":"doc:\/\/com.mapbox.navigation\/documentation\/MapboxDirections\/RoadClasses","type":"reference"},{"type":"text","text":" exclusion violation case."}],"identifier":"doc:\/\/com.mapbox.navigation\/documentation\/MapboxDirections\/RoadClassExclusionViolation","role":"symbol","navigatorTitle":[{"text":"RoadClassExclusionViolation","kind":"identifier"}],"title":"RoadClassExclusionViolation","url":"\/documentation\/mapboxdirections\/roadclassexclusionviolation","fragments":[{"text":"struct","kind":"keyword"},{"text":" ","kind":"text"},{"kind":"identifier","text":"RoadClassExclusionViolation"}],"type":"topic","kind":"symbol"},"doc://com.mapbox.navigation/documentation/MapboxDirections/AmenityType":{"title":"AmenityType","abstract":[{"text":"Type of the ","type":"text"},{"isActive":true,"identifier":"doc:\/\/com.mapbox.navigation\/documentation\/MapboxDirections\/Amenity","type":"reference"},{"type":"text","text":"."}],"url":"\/documentation\/mapboxdirections\/amenitytype","identifier":"doc:\/\/com.mapbox.navigation\/documentation\/MapboxDirections\/AmenityType","fragments":[{"text":"enum","kind":"keyword"},{"text":" ","kind":"text"},{"text":"AmenityType","kind":"identifier"}],"type":"topic","role":"symbol","navigatorTitle":[{"text":"AmenityType","kind":"identifier"}],"kind":"symbol"},"doc://com.mapbox.navigation/documentation/MapboxDirections/TransportType":{"url":"\/documentation\/mapboxdirections\/transporttype","kind":"symbol","navigatorTitle":[{"text":"TransportType","kind":"identifier"}],"title":"TransportType","abstract":[{"text":"A ","type":"text"},{"identifier":"doc:\/\/com.mapbox.navigation\/documentation\/MapboxDirections\/TransportType","isActive":true,"type":"reference"},{"type":"text","text":" specifies the mode of transportation used for part of a route."}],"type":"topic","role":"symbol","fragments":[{"text":"enum","kind":"keyword"},{"text":" ","kind":"text"},{"text":"TransportType","kind":"identifier"}],"identifier":"doc:\/\/com.mapbox.navigation\/documentation\/MapboxDirections\/TransportType"},"doc://com.mapbox.navigation/documentation/MapboxDirections/DrivingSide":{"identifier":"doc:\/\/com.mapbox.navigation\/documentation\/MapboxDirections\/DrivingSide","navigatorTitle":[{"kind":"identifier","text":"DrivingSide"}],"fragments":[{"text":"enum","kind":"keyword"},{"text":" ","kind":"text"},{"text":"DrivingSide","kind":"identifier"}],"abstract":[{"text":"A ","type":"text"},{"type":"codeVoice","code":"DrivingSide"},{"text":" indicates which side of the road cars and traffic flow.","type":"text"}],"kind":"symbol","type":"topic","url":"\/documentation\/mapboxdirections\/drivingside","title":"DrivingSide","role":"symbol"},"https://wiki.openstreetmap.org/wiki/Tag:highway%3Drest_area":{"url":"https:\/\/wiki.openstreetmap.org\/wiki\/Tag:highway%3Drest_area","type":"link","title":"rest stop","titleInlineContent":[{"type":"text","text":"rest stop"}],"identifier":"https:\/\/wiki.openstreetmap.org\/wiki\/Tag:highway%3Drest_area"},"doc://com.mapbox.navigation/documentation/MapboxDirections/RouteOptions":{"abstract":[{"type":"text","text":"A "},{"identifier":"doc:\/\/com.mapbox.navigation\/documentation\/MapboxDirections\/RouteOptions","isActive":true,"type":"reference"},{"text":" object is a structure that specifies the criteria for results returned by the Mapbox Directions","type":"text"},{"text":" ","type":"text"},{"type":"text","text":"API."}],"identifier":"doc:\/\/com.mapbox.navigation\/documentation\/MapboxDirections\/RouteOptions","url":"\/documentation\/mapboxdirections\/routeoptions","title":"RouteOptions","role":"symbol","fragments":[{"kind":"keyword","text":"class"},{"kind":"text","text":" "},{"text":"RouteOptions","kind":"identifier"}],"navigatorTitle":[{"text":"RouteOptions","kind":"identifier"}],"kind":"symbol","type":"topic"},"doc://com.mapbox.navigation/documentation/MapboxDirections/CustomOptionComparisonPolicy":{"fragments":[{"kind":"keyword","text":"enum"},{"text":" ","kind":"text"},{"kind":"identifier","text":"CustomOptionComparisonPolicy"}],"role":"symbol","url":"\/documentation\/mapboxdirections\/customoptioncomparisonpolicy","abstract":[{"text":"Describes how ","type":"text"},{"type":"reference","identifier":"doc:\/\/com.mapbox.navigation\/documentation\/MapboxDirections\/CustomValueOptionSet\/customOptionsByRawValue","isActive":true},{"type":"text","text":" component is compared during logical operations in"},{"type":"text","text":" "},{"identifier":"doc:\/\/com.mapbox.navigation\/documentation\/MapboxDirections\/CustomValueOptionSet","type":"reference","isActive":true},{"type":"text","text":"."}],"identifier":"doc:\/\/com.mapbox.navigation\/documentation\/MapboxDirections\/CustomOptionComparisonPolicy","navigatorTitle":[{"text":"CustomOptionComparisonPolicy","kind":"identifier"}],"type":"topic","title":"CustomOptionComparisonPolicy","kind":"symbol"},"doc://com.mapbox.navigation/documentation/MapboxDirections/MatrixOptions":{"title":"MatrixOptions","abstract":[{"type":"text","text":"Options for calculating matrices from the Mapbox Matrix service."}],"url":"\/documentation\/mapboxdirections\/matrixoptions","identifier":"doc:\/\/com.mapbox.navigation\/documentation\/MapboxDirections\/MatrixOptions","fragments":[{"text":"class","kind":"keyword"},{"text":" ","kind":"text"},{"kind":"identifier","text":"MatrixOptions"}],"type":"topic","role":"symbol","navigatorTitle":[{"text":"MatrixOptions","kind":"identifier"}],"kind":"symbol"},"doc://com.mapbox.navigation/documentation/MapboxDirections/BlockedLanes":{"abstract":[{"type":"text","text":"Defines a lane affected by the "},{"type":"reference","identifier":"doc:\/\/com.mapbox.navigation\/documentation\/MapboxDirections\/Incident","isActive":true}],"identifier":"doc:\/\/com.mapbox.navigation\/documentation\/MapboxDirections\/BlockedLanes","url":"\/documentation\/mapboxdirections\/blockedlanes","title":"BlockedLanes","role":"symbol","fragments":[{"kind":"keyword","text":"struct"},{"text":" ","kind":"text"},{"text":"BlockedLanes","kind":"identifier"}],"navigatorTitle":[{"text":"BlockedLanes","kind":"identifier"}],"kind":"symbol","type":"topic"},"doc://com.mapbox.navigation/documentation/MapboxDirections/MBDirectionsProfileIdentifier":{"identifier":"doc:\/\/com.mapbox.navigation\/documentation\/MapboxDirections\/MBDirectionsProfileIdentifier","title":"MBDirectionsProfileIdentifier","type":"topic","navigatorTitle":[{"kind":"identifier","text":"MBDirectionsProfileIdentifier"}],"url":"\/documentation\/mapboxdirections\/mbdirectionsprofileidentifier","kind":"symbol","role":"symbol","abstract":[],"fragments":[{"text":"typealias","kind":"keyword"},{"text":" ","kind":"text"},{"text":"MBDirectionsProfileIdentifier","kind":"identifier"}],"deprecated":true},"doc://com.mapbox.navigation/documentation/MapboxDirections/MBDirectionsPriority":{"type":"topic","title":"MBDirectionsPriority","identifier":"doc:\/\/com.mapbox.navigation\/documentation\/MapboxDirections\/MBDirectionsPriority","navigatorTitle":[{"kind":"identifier","text":"MBDirectionsPriority"}],"url":"\/documentation\/mapboxdirections\/mbdirectionspriority","kind":"symbol","role":"symbol","abstract":[],"fragments":[{"text":"typealias","kind":"keyword"},{"text":" ","kind":"text"},{"text":"MBDirectionsPriority","kind":"identifier"}],"deprecated":true},"doc://com.mapbox.navigation/documentation/MapboxDirections/Polyline":{"type":"topic","kind":"symbol","navigatorTitle":[{"text":"Polyline","kind":"identifier"}],"identifier":"doc:\/\/com.mapbox.navigation\/documentation\/MapboxDirections\/Polyline","role":"symbol","url":"\/documentation\/mapboxdirections\/polyline","title":"Polyline","fragments":[{"text":"struct","kind":"keyword"},{"kind":"text","text":" "},{"text":"Polyline","kind":"identifier"}],"abstract":[{"text":"This class can be used for :","type":"text"}]},"doc://com.mapbox.navigation/documentation/MapboxDirections/Route":{"navigatorTitle":[{"kind":"identifier","text":"Route"}],"title":"Route","abstract":[{"type":"text","text":"A "},{"type":"reference","identifier":"doc:\/\/com.mapbox.navigation\/documentation\/MapboxDirections\/Route","isActive":true},{"text":" object defines a single route that the user can follow to visit a series of waypoints in order. The","type":"text"},{"type":"text","text":" "},{"text":"route object includes information about the route, such as its distance and expected travel time. Depending on the","type":"text"},{"text":" ","type":"text"},{"type":"text","text":"criteria used to calculate the route, the route object may also include detailed turn-by-turn instructions."}],"url":"\/documentation\/mapboxdirections\/route","identifier":"doc:\/\/com.mapbox.navigation\/documentation\/MapboxDirections\/Route","fragments":[{"text":"struct","kind":"keyword"},{"text":" ","kind":"text"},{"kind":"identifier","text":"Route"}],"type":"topic","kind":"symbol","role":"symbol"},"doc://com.mapbox.navigation/documentation/MapboxDirections/OfflineDirectionsProtocol":{"role":"symbol","type":"topic","identifier":"doc:\/\/com.mapbox.navigation\/documentation\/MapboxDirections\/OfflineDirectionsProtocol","url":"\/documentation\/mapboxdirections\/offlinedirectionsprotocol","abstract":[],"navigatorTitle":[{"text":"OfflineDirectionsProtocol","kind":"identifier"}],"fragments":[{"text":"protocol","kind":"keyword"},{"kind":"text","text":" "},{"text":"OfflineDirectionsProtocol","kind":"identifier"}],"title":"OfflineDirectionsProtocol","kind":"symbol"},"https://docs.mapbox.com/api/navigation/map-matching/":{"titleInlineContent":[{"type":"text","text":"Mapbox Map Matching API"}],"url":"https:\/\/docs.mapbox.com\/api\/navigation\/map-matching\/","title":"Mapbox Map Matching API","identifier":"https:\/\/docs.mapbox.com\/api\/navigation\/map-matching\/","type":"link"},"doc://com.mapbox.navigation/documentation/MapboxDirections/Intersection":{"fragments":[{"kind":"keyword","text":"struct"},{"text":" ","kind":"text"},{"text":"Intersection","kind":"identifier"}],"identifier":"doc:\/\/com.mapbox.navigation\/documentation\/MapboxDirections\/Intersection","navigatorTitle":[{"text":"Intersection","kind":"identifier"}],"title":"Intersection","type":"topic","role":"symbol","kind":"symbol","abstract":[{"type":"text","text":"A single cross street along a step."}],"url":"\/documentation\/mapboxdirections\/intersection"},"doc://com.mapbox.navigation/documentation/MapboxDirections/RouteResponse":{"url":"\/documentation\/mapboxdirections\/routeresponse","abstract":[{"text":"A ","type":"text"},{"identifier":"doc:\/\/com.mapbox.navigation\/documentation\/MapboxDirections\/RouteResponse","type":"reference","isActive":true},{"type":"text","text":" object is a structure that corresponds to a directions response returned by the Mapbox"},{"text":" ","type":"text"},{"type":"text","text":"Directions API."}],"title":"RouteResponse","kind":"symbol","identifier":"doc:\/\/com.mapbox.navigation\/documentation\/MapboxDirections\/RouteResponse","role":"symbol","fragments":[{"kind":"keyword","text":"struct"},{"text":" ","kind":"text"},{"kind":"identifier","text":"RouteResponse"}],"navigatorTitle":[{"kind":"identifier","text":"RouteResponse"}],"type":"topic"},"doc://com.mapbox.navigation/documentation/MapboxDirections/encodeLevels(_:)":{"type":"topic","title":"encodeLevels(_:)","identifier":"doc:\/\/com.mapbox.navigation\/documentation\/MapboxDirections\/encodeLevels(_:)","url":"\/documentation\/mapboxdirections\/encodelevels(_:)","kind":"symbol","role":"symbol","abstract":[{"type":"text","text":"This function encodes an "},{"type":"codeVoice","code":"[UInt32]"},{"text":" to a ","type":"text"},{"type":"codeVoice","code":"String"}],"fragments":[{"text":"func","kind":"keyword"},{"text":" ","kind":"text"},{"text":"encodeLevels","kind":"identifier"},{"kind":"text","text":"(["},{"preciseIdentifier":"s:s6UInt32V","text":"UInt32","kind":"typeIdentifier"},{"text":"]) -> ","kind":"text"},{"text":"String","kind":"typeIdentifier","preciseIdentifier":"s:SS"}]},"doc://com.mapbox.navigation/documentation/MapboxDirections/OfflineVersionsHandler":{"identifier":"doc:\/\/com.mapbox.navigation\/documentation\/MapboxDirections\/OfflineVersionsHandler","title":"OfflineVersionsHandler","type":"topic","navigatorTitle":[{"kind":"identifier","text":"OfflineVersionsHandler"}],"url":"\/documentation\/mapboxdirections\/offlineversionshandler","kind":"symbol","role":"symbol","abstract":[],"fragments":[{"text":"typealias","kind":"keyword"},{"text":" ","kind":"text"},{"text":"OfflineVersionsHandler","kind":"identifier"}]},"doc://com.mapbox.navigation/documentation/MapboxDirections/ManeuverDirection":{"kind":"symbol","identifier":"doc:\/\/com.mapbox.navigation\/documentation\/MapboxDirections\/ManeuverDirection","role":"symbol","type":"topic","abstract":[{"type":"text","text":"A "},{"identifier":"doc:\/\/com.mapbox.navigation\/documentation\/MapboxDirections\/ManeuverDirection","isActive":true,"type":"reference"},{"text":" clarifies a ","type":"text"},{"isActive":true,"type":"reference","identifier":"doc:\/\/com.mapbox.navigation\/documentation\/MapboxDirections\/ManeuverType"},{"type":"text","text":" with directional information. The exact meaning of the maneuver"},{"text":" ","type":"text"},{"text":"direction for a given step depends on the step’s maneuver type; see the ","type":"text"},{"type":"reference","identifier":"doc:\/\/com.mapbox.navigation\/documentation\/MapboxDirections\/ManeuverType","isActive":true},{"text":" documentation for details.","type":"text"}],"fragments":[{"text":"enum","kind":"keyword"},{"text":" ","kind":"text"},{"text":"ManeuverDirection","kind":"identifier"}],"navigatorTitle":[{"kind":"identifier","text":"ManeuverDirection"}],"url":"\/documentation\/mapboxdirections\/maneuverdirection","title":"ManeuverDirection"},"doc://com.mapbox.navigation/documentation/MapboxDirections/ProfileIdentifier":{"type":"topic","identifier":"doc:\/\/com.mapbox.navigation\/documentation\/MapboxDirections\/ProfileIdentifier","fragments":[{"kind":"keyword","text":"struct"},{"kind":"text","text":" "},{"text":"ProfileIdentifier","kind":"identifier"}],"abstract":[{"text":"Options determining the primary mode of transportation.","type":"text"}],"url":"\/documentation\/mapboxdirections\/profileidentifier","title":"ProfileIdentifier","navigatorTitle":[{"kind":"identifier","text":"ProfileIdentifier"}],"kind":"symbol","role":"symbol"},"doc://com.mapbox.navigation/documentation/MapboxDirections/SignStandard":{"type":"topic","title":"SignStandard","identifier":"doc:\/\/com.mapbox.navigation\/documentation\/MapboxDirections\/SignStandard","navigatorTitle":[{"text":"SignStandard","kind":"identifier"}],"url":"\/documentation\/mapboxdirections\/signstandard","kind":"symbol","role":"symbol","abstract":[{"type":"text","text":"A road sign design standard."}],"fragments":[{"text":"enum","kind":"keyword"},{"text":" ","kind":"text"},{"kind":"identifier","text":"SignStandard"}]},"doc://com.mapbox.navigation/documentation/MapboxDirections/DirectionsProfileIdentifier":{"identifier":"doc:\/\/com.mapbox.navigation\/documentation\/MapboxDirections\/DirectionsProfileIdentifier","title":"DirectionsProfileIdentifier","type":"topic","navigatorTitle":[{"text":"DirectionsProfileIdentifier","kind":"identifier"}],"url":"\/documentation\/mapboxdirections\/directionsprofileidentifier","kind":"symbol","role":"symbol","abstract":[{"type":"text","text":"Options determining the primary mode of transportation for the routes."}],"fragments":[{"text":"typealias","kind":"keyword"},{"text":" ","kind":"text"},{"text":"DirectionsProfileIdentifier","kind":"identifier"}],"deprecated":true},"doc://com.mapbox.navigation/documentation/MapboxDirections/CustomValueOptionSet":{"fragments":[{"kind":"keyword","text":"protocol"},{"text":" ","kind":"text"},{"text":"CustomValueOptionSet","kind":"identifier"}],"role":"symbol","url":"\/documentation\/mapboxdirections\/customvalueoptionset","abstract":[{"type":"text","text":"Option set implementation which allows each option to have custom string value attached."}],"identifier":"doc:\/\/com.mapbox.navigation\/documentation\/MapboxDirections\/CustomValueOptionSet","navigatorTitle":[{"kind":"identifier","text":"CustomValueOptionSet"}],"type":"topic","title":"CustomValueOptionSet","kind":"symbol"},"doc://com.mapbox.navigation/documentation/MapboxDirections/decodePolyline(_:precision:)-2ues4":{"type":"topic","title":"decodePolyline(_:precision:)","identifier":"doc:\/\/com.mapbox.navigation\/documentation\/MapboxDirections\/decodePolyline(_:precision:)-2ues4","url":"\/documentation\/mapboxdirections\/decodepolyline(_:precision:)-2ues4","kind":"symbol","role":"symbol","abstract":[{"type":"text","text":"This function decodes a "},{"code":"String","type":"codeVoice"},{"type":"text","text":" to a "},{"code":"[CLLocationCoordinate2D]?","type":"codeVoice"}],"fragments":[{"text":"func","kind":"keyword"},{"text":" ","kind":"text"},{"text":"decodePolyline","kind":"identifier"},{"kind":"text","text":"("},{"text":"String","preciseIdentifier":"s:SS","kind":"typeIdentifier"},{"text":", ","kind":"text"},{"text":"precision","kind":"externalParam"},{"text":": ","kind":"text"},{"preciseIdentifier":"s:Sd","kind":"typeIdentifier","text":"Double"},{"kind":"text","text":") -> ["},{"text":"LocationCoordinate2D","preciseIdentifier":"s:16MapboxDirections20LocationCoordinate2Da","kind":"typeIdentifier"},{"text":"]?","kind":"text"}]},"doc://com.mapbox.navigation/documentation/MapboxDirections/Credentials":{"title":"Credentials","abstract":[],"url":"\/documentation\/mapboxdirections\/credentials","identifier":"doc:\/\/com.mapbox.navigation\/documentation\/MapboxDirections\/Credentials","fragments":[{"text":"struct","kind":"keyword"},{"text":" ","kind":"text"},{"kind":"identifier","text":"Credentials"}],"type":"topic","role":"symbol","navigatorTitle":[{"text":"Credentials","kind":"identifier"}],"kind":"symbol"},"doc://com.mapbox.navigation/documentation/MapboxDirections/encodeCoordinates(_:precision:)":{"title":"encodeCoordinates(_:precision:)","abstract":[{"type":"text","text":"This function encodes an "},{"type":"codeVoice","code":"[CLLocationCoordinate2D]"},{"text":" to a ","type":"text"},{"code":"String","type":"codeVoice"}],"url":"\/documentation\/mapboxdirections\/encodecoordinates(_:precision:)","identifier":"doc:\/\/com.mapbox.navigation\/documentation\/MapboxDirections\/encodeCoordinates(_:precision:)","fragments":[{"text":"func","kind":"keyword"},{"kind":"text","text":" "},{"text":"encodeCoordinates","kind":"identifier"},{"kind":"text","text":"(["},{"kind":"typeIdentifier","preciseIdentifier":"s:16MapboxDirections20LocationCoordinate2Da","text":"LocationCoordinate2D"},{"text":"], ","kind":"text"},{"text":"precision","kind":"externalParam"},{"text":": ","kind":"text"},{"text":"Double","preciseIdentifier":"s:Sd","kind":"typeIdentifier"},{"kind":"text","text":") -> "},{"kind":"typeIdentifier","preciseIdentifier":"s:SS","text":"String"}],"type":"topic","role":"symbol","kind":"symbol"},"doc://com.mapbox.navigation/documentation/MapboxDirections/Match":{"title":"Match","role":"symbol","fragments":[{"kind":"keyword","text":"struct"},{"text":" ","kind":"text"},{"text":"Match","kind":"identifier"}],"url":"\/documentation\/mapboxdirections\/match","abstract":[{"type":"text","text":"A "},{"identifier":"doc:\/\/com.mapbox.navigation\/documentation\/MapboxDirections\/Match","type":"reference","isActive":true},{"text":" object defines a single route that was created from a series of points that were matched against a road","type":"text"},{"text":" ","type":"text"},{"text":"network.","type":"text"}],"navigatorTitle":[{"text":"Match","kind":"identifier"}],"kind":"symbol","type":"topic","identifier":"doc:\/\/com.mapbox.navigation\/documentation\/MapboxDirections\/Match"},"doc://com.mapbox.navigation/documentation/MapboxDirections/Interchange":{"identifier":"doc:\/\/com.mapbox.navigation\/documentation\/MapboxDirections\/Interchange","url":"\/documentation\/mapboxdirections\/interchange","title":"Interchange","abstract":[{"type":"text","text":"Contains information about routing and passing interchange along the route."}],"fragments":[{"text":"struct","kind":"keyword"},{"text":" ","kind":"text"},{"text":"Interchange","kind":"identifier"}],"navigatorTitle":[{"kind":"identifier","text":"Interchange"}],"role":"symbol","kind":"symbol","type":"topic"},"doc://com.mapbox.navigation/documentation/MapboxDirections/DirectionsResult":{"role":"symbol","url":"\/documentation\/mapboxdirections\/directionsresult","kind":"symbol","type":"topic","identifier":"doc:\/\/com.mapbox.navigation\/documentation\/MapboxDirections\/DirectionsResult","navigatorTitle":[{"kind":"identifier","text":"DirectionsResult"}],"abstract":[{"text":"A ","type":"text"},{"code":"DirectionsResult","type":"codeVoice"},{"type":"text","text":" represents a result returned from either the Mapbox Directions service."}],"fragments":[{"text":"protocol","kind":"keyword"},{"kind":"text","text":" "},{"text":"DirectionsResult","kind":"identifier"}],"title":"DirectionsResult"},"doc://com.mapbox.navigation/documentation/MapboxDirections/DirectionsResultCodingKeys":{"fragments":[{"text":"enum","kind":"keyword"},{"text":" ","kind":"text"},{"text":"DirectionsResultCodingKeys","kind":"identifier"}],"abstract":[],"url":"\/documentation\/mapboxdirections\/directionsresultcodingkeys","navigatorTitle":[{"text":"DirectionsResultCodingKeys","kind":"identifier"}],"role":"symbol","type":"topic","kind":"symbol","title":"DirectionsResultCodingKeys","identifier":"doc:\/\/com.mapbox.navigation\/documentation\/MapboxDirections\/DirectionsResultCodingKeys"},"doc://com.mapbox.navigation/documentation/MapboxDirections/encodeLocations(_:precision:)":{"identifier":"doc:\/\/com.mapbox.navigation\/documentation\/MapboxDirections\/encodeLocations(_:precision:)","title":"encodeLocations(_:precision:)","type":"topic","url":"\/documentation\/mapboxdirections\/encodelocations(_:precision:)","kind":"symbol","role":"symbol","abstract":[{"text":"This function encodes an ","type":"text"},{"type":"codeVoice","code":"[CLLocation]"},{"type":"text","text":" to a "},{"code":"String","type":"codeVoice"}],"fragments":[{"text":"func","kind":"keyword"},{"text":" ","kind":"text"},{"text":"encodeLocations","kind":"identifier"},{"text":"([","kind":"text"},{"kind":"typeIdentifier","preciseIdentifier":"c:objc(cs)CLLocation","text":"CLLocation"},{"text":"], ","kind":"text"},{"text":"precision","kind":"externalParam"},{"text":": ","kind":"text"},{"kind":"typeIdentifier","text":"Double","preciseIdentifier":"s:Sd"},{"text":") -> ","kind":"text"},{"preciseIdentifier":"s:SS","text":"String","kind":"typeIdentifier"}]},"doc://com.mapbox.navigation/documentation/MapboxDirections/TollCategory":{"title":"TollCategory","url":"\/documentation\/mapboxdirections\/tollcategory","abstract":[{"text":"Categories by which toll fees are divided.","type":"text"}],"fragments":[{"kind":"keyword","text":"struct"},{"text":" ","kind":"text"},{"text":"TollCategory","kind":"identifier"}],"navigatorTitle":[{"text":"TollCategory","kind":"identifier"}],"kind":"symbol","identifier":"doc:\/\/com.mapbox.navigation\/documentation\/MapboxDirections\/TollCategory","type":"topic","role":"symbol"},"doc://com.mapbox.navigation/documentation/MapboxDirections/AdministrativeRegion":{"title":"AdministrativeRegion","kind":"symbol","role":"symbol","url":"\/documentation\/mapboxdirections\/administrativeregion","type":"topic","fragments":[{"kind":"keyword","text":"struct"},{"kind":"text","text":" "},{"kind":"identifier","text":"AdministrativeRegion"}],"navigatorTitle":[{"text":"AdministrativeRegion","kind":"identifier"}],"abstract":[{"type":"reference","identifier":"doc:\/\/com.mapbox.navigation\/documentation\/MapboxDirections\/AdministrativeRegion","isActive":true},{"type":"text","text":" describes corresponding object on the route."}],"identifier":"doc:\/\/com.mapbox.navigation\/documentation\/MapboxDirections\/AdministrativeRegion"},"doc://com.mapbox.navigation/documentation/MapboxDirections/ForeignMemberContainerClass":{"fragments":[{"text":"protocol","kind":"keyword"},{"text":" ","kind":"text"},{"kind":"identifier","text":"ForeignMemberContainerClass"}],"abstract":[{"type":"text","text":"A class that can contain foreign members in arbitrary keys."}],"url":"\/documentation\/mapboxdirections\/foreignmembercontainerclass","identifier":"doc:\/\/com.mapbox.navigation\/documentation\/MapboxDirections\/ForeignMemberContainerClass","kind":"symbol","title":"ForeignMemberContainerClass","type":"topic","role":"symbol","navigatorTitle":[{"text":"ForeignMemberContainerClass","kind":"identifier"}]},"doc://com.mapbox.navigation/documentation/MapboxDirections/RestStop":{"kind":"symbol","identifier":"doc:\/\/com.mapbox.navigation\/documentation\/MapboxDirections\/RestStop","role":"symbol","type":"topic","abstract":[{"text":"A ","type":"text"},{"identifier":"https:\/\/wiki.openstreetmap.org\/wiki\/Tag:highway%3Drest_area","type":"reference","isActive":true},{"text":" along the route.","type":"text"}],"fragments":[{"kind":"keyword","text":"struct"},{"kind":"text","text":" "},{"text":"RestStop","kind":"identifier"}],"navigatorTitle":[{"kind":"identifier","text":"RestStop"}],"url":"\/documentation\/mapboxdirections\/reststop","title":"RestStop"},"doc://com.mapbox.navigation/documentation/MapboxDirections/Amenity":{"title":"Amenity","abstract":[{"text":"Provides information about amenity that is available at a given ","type":"text"},{"type":"reference","identifier":"doc:\/\/com.mapbox.navigation\/documentation\/MapboxDirections\/RestStop","isActive":true},{"text":".","type":"text"}],"url":"\/documentation\/mapboxdirections\/amenity","identifier":"doc:\/\/com.mapbox.navigation\/documentation\/MapboxDirections\/Amenity","fragments":[{"text":"struct","kind":"keyword"},{"text":" ","kind":"text"},{"text":"Amenity","kind":"identifier"}],"type":"topic","role":"symbol","navigatorTitle":[{"text":"Amenity","kind":"identifier"}],"kind":"symbol"},"doc://com.mapbox.navigation/documentation/MapboxDirections/LaneIndication":{"identifier":"doc:\/\/com.mapbox.navigation\/documentation\/MapboxDirections\/LaneIndication","abstract":[{"type":"text","text":"Each of these options specifies a maneuver direction for which a given lane can be used."}],"title":"LaneIndication","url":"\/documentation\/mapboxdirections\/laneindication","kind":"symbol","role":"symbol","fragments":[{"text":"struct","kind":"keyword"},{"kind":"text","text":" "},{"kind":"identifier","text":"LaneIndication"}],"navigatorTitle":[{"kind":"identifier","text":"LaneIndication"}],"type":"topic"},"doc://com.mapbox.navigation/documentation/MapboxDirections/CongestionLevel":{"navigatorTitle":[{"text":"CongestionLevel","kind":"identifier"}],"identifier":"doc:\/\/com.mapbox.navigation\/documentation\/MapboxDirections\/CongestionLevel","abstract":[{"type":"text","text":"A "},{"identifier":"doc:\/\/com.mapbox.navigation\/documentation\/MapboxDirections\/CongestionLevel","isActive":true,"type":"reference"},{"type":"text","text":" indicates the level of traffic congestion along a road segment relative to the normal flow of"},{"text":" ","type":"text"},{"type":"text","text":"traffic along that segment. You can color-code a route line according to the congestion level along each segment of"},{"type":"text","text":" "},{"type":"text","text":"the route."}],"kind":"symbol","role":"symbol","title":"CongestionLevel","type":"topic","url":"\/documentation\/mapboxdirections\/congestionlevel","fragments":[{"text":"enum","kind":"keyword"},{"text":" ","kind":"text"},{"text":"CongestionLevel","kind":"identifier"}]},"doc://com.mapbox.navigation/documentation/MapboxDirections/RefreshedRoute":{"navigatorTitle":[{"kind":"identifier","text":"RefreshedRoute"}],"kind":"symbol","identifier":"doc:\/\/com.mapbox.navigation\/documentation\/MapboxDirections\/RefreshedRoute","type":"topic","title":"RefreshedRoute","abstract":[{"type":"text","text":"A skeletal route containing only the information about the route that has been refreshed."}],"role":"symbol","fragments":[{"kind":"keyword","text":"struct"},{"kind":"text","text":" "},{"text":"RefreshedRoute","kind":"identifier"}],"url":"\/documentation\/mapboxdirections\/refreshedroute"},"doc://com.mapbox.navigation/documentation/MapboxDirections/Isochrones":{"identifier":"doc:\/\/com.mapbox.navigation\/documentation\/MapboxDirections\/Isochrones","title":"Isochrones","type":"topic","navigatorTitle":[{"text":"Isochrones","kind":"identifier"}],"url":"\/documentation\/mapboxdirections\/isochrones","kind":"symbol","role":"symbol","abstract":[{"type":"text","text":"Computes areas that are reachable within a specified amount of time or distance from a location, and returns the"},{"text":" ","type":"text"},{"type":"text","text":"reachable regions as contours of polygons or lines that you can display on a map."}],"fragments":[{"text":"class","kind":"keyword"},{"text":" ","kind":"text"},{"kind":"identifier","text":"Isochrones"}]},"doc://com.mapbox.navigation/documentation/MapboxDirections/MatrixError":{"url":"\/documentation\/mapboxdirections\/matrixerror","kind":"symbol","abstract":[{"type":"text","text":"An error that occurs when computing matrices."}],"type":"topic","fragments":[{"kind":"keyword","text":"enum"},{"text":" ","kind":"text"},{"kind":"identifier","text":"MatrixError"}],"title":"MatrixError","identifier":"doc:\/\/com.mapbox.navigation\/documentation\/MapboxDirections\/MatrixError","role":"symbol","navigatorTitle":[{"text":"MatrixError","kind":"identifier"}]},"doc://com.mapbox.navigation/documentation/MapboxDirections/Scale":{"type":"topic","title":"Scale","identifier":"doc:\/\/com.mapbox.navigation\/documentation\/MapboxDirections\/Scale","navigatorTitle":[{"text":"Scale","kind":"identifier"}],"url":"\/documentation\/mapboxdirections\/scale","kind":"symbol","role":"symbol","abstract":[{"text":"An image scale factor.","type":"text"}],"fragments":[{"text":"typealias","kind":"keyword"},{"kind":"text","text":" "},{"text":"Scale","kind":"identifier"}]},"doc://com.mapbox.navigation/documentation/MapboxDirections/DirectionsError":{"role":"symbol","type":"topic","url":"\/documentation\/mapboxdirections\/directionserror","identifier":"doc:\/\/com.mapbox.navigation\/documentation\/MapboxDirections\/DirectionsError","navigatorTitle":[{"text":"DirectionsError","kind":"identifier"}],"title":"DirectionsError","abstract":[{"type":"text","text":"An error that occurs when calculating directions."}],"kind":"symbol","fragments":[{"kind":"keyword","text":"enum"},{"text":" ","kind":"text"},{"text":"DirectionsError","kind":"identifier"}]},"doc://com.mapbox.navigation/documentation/MapboxDirections/MatchOptions":{"kind":"symbol","abstract":[{"type":"text","text":"A "},{"isActive":true,"type":"reference","identifier":"doc:\/\/com.mapbox.navigation\/documentation\/MapboxDirections\/MatchOptions"},{"text":" object is a structure that specifies the criteria for results returned by the Mapbox Map Matching","type":"text"},{"text":" ","type":"text"},{"type":"text","text":"API."}],"url":"\/documentation\/mapboxdirections\/matchoptions","type":"topic","title":"MatchOptions","role":"symbol","fragments":[{"kind":"keyword","text":"class"},{"text":" ","kind":"text"},{"text":"MatchOptions","kind":"identifier"}],"identifier":"doc:\/\/com.mapbox.navigation\/documentation\/MapboxDirections\/MatchOptions","navigatorTitle":[{"text":"MatchOptions","kind":"identifier"}]},"doc://com.mapbox.navigation/documentation/MapboxDirections/Waypoint":{"title":"Waypoint","abstract":[{"text":"A ","type":"text"},{"type":"reference","identifier":"doc:\/\/com.mapbox.navigation\/documentation\/MapboxDirections\/Waypoint","isActive":true},{"text":" object indicates a location along a route. It may be the route’s origin or destination, or it may be","type":"text"},{"type":"text","text":" "},{"type":"text","text":"another location that the route visits. A waypoint object indicates the location’s geographic location along with"},{"text":" ","type":"text"},{"type":"text","text":"other optional information, such as a name or the user’s direction approaching the waypoint. You create a"},{"type":"text","text":" "},{"identifier":"doc:\/\/com.mapbox.navigation\/documentation\/MapboxDirections\/RouteOptions","isActive":true,"type":"reference"},{"text":" object using waypoint objects and also receive waypoint objects in the completion handler of the","type":"text"},{"type":"text","text":" "},{"code":"Directions.calculate(_:completionHandler:)","type":"codeVoice"},{"type":"text","text":" method."}],"url":"\/documentation\/mapboxdirections\/waypoint","identifier":"doc:\/\/com.mapbox.navigation\/documentation\/MapboxDirections\/Waypoint","fragments":[{"text":"struct","kind":"keyword"},{"kind":"text","text":" "},{"kind":"identifier","text":"Waypoint"}],"type":"topic","role":"symbol","navigatorTitle":[{"text":"Waypoint","kind":"identifier"}],"kind":"symbol"},"https://docs.mapbox.com/api/navigation/matrix/":{"titleInlineContent":[{"type":"text","text":"Mapbox Matrix API"}],"url":"https:\/\/docs.mapbox.com\/api\/navigation\/matrix\/","title":"Mapbox Matrix API","identifier":"https:\/\/docs.mapbox.com\/api\/navigation\/matrix\/","type":"link"},"doc://com.mapbox.navigation/documentation/MapboxDirections/ManeuverType":{"kind":"symbol","identifier":"doc:\/\/com.mapbox.navigation\/documentation\/MapboxDirections\/ManeuverType","role":"symbol","type":"topic","abstract":[{"type":"text","text":"A "},{"type":"reference","identifier":"doc:\/\/com.mapbox.navigation\/documentation\/MapboxDirections\/ManeuverType","isActive":true},{"text":" specifies the type of maneuver required to complete the route step. You can pair a maneuver type","type":"text"},{"type":"text","text":" "},{"text":"with a ","type":"text"},{"type":"reference","identifier":"doc:\/\/com.mapbox.navigation\/documentation\/MapboxDirections\/ManeuverDirection","isActive":true},{"text":" to choose an appropriate visual or voice prompt to present the user.","type":"text"}],"fragments":[{"kind":"keyword","text":"enum"},{"kind":"text","text":" "},{"kind":"identifier","text":"ManeuverType"}],"navigatorTitle":[{"text":"ManeuverType","kind":"identifier"}],"url":"\/documentation\/mapboxdirections\/maneuvertype","title":"ManeuverType"},"doc://com.mapbox.navigation/documentation/MapboxDirections/VisualInstructionBanner":{"type":"topic","title":"VisualInstructionBanner","identifier":"doc:\/\/com.mapbox.navigation\/documentation\/MapboxDirections\/VisualInstructionBanner","navigatorTitle":[{"text":"VisualInstructionBanner","kind":"identifier"}],"url":"\/documentation\/mapboxdirections\/visualinstructionbanner","kind":"symbol","role":"symbol","abstract":[{"type":"text","text":"A visual instruction banner contains all the information necessary for creating a visual cue about a given"},{"text":" ","type":"text"},{"type":"reference","identifier":"doc:\/\/com.mapbox.navigation\/documentation\/MapboxDirections\/RouteStep","isActive":true},{"text":".","type":"text"}],"fragments":[{"text":"struct","kind":"keyword"},{"text":" ","kind":"text"},{"kind":"identifier","text":"VisualInstructionBanner"}]},"doc://com.mapbox.navigation/documentation/MapboxDirections/decodePolyline(_:precision:)-1gxs5":{"identifier":"doc:\/\/com.mapbox.navigation\/documentation\/MapboxDirections\/decodePolyline(_:precision:)-1gxs5","title":"decodePolyline(_:precision:)","type":"topic","url":"\/documentation\/mapboxdirections\/decodepolyline(_:precision:)-1gxs5","kind":"symbol","role":"symbol","abstract":[{"type":"text","text":"This function decodes a String to a [CLLocation]?"}],"fragments":[{"text":"func","kind":"keyword"},{"text":" ","kind":"text"},{"text":"decodePolyline","kind":"identifier"},{"text":"(","kind":"text"},{"text":"String","preciseIdentifier":"s:SS","kind":"typeIdentifier"},{"kind":"text","text":", "},{"text":"precision","kind":"externalParam"},{"text":": ","kind":"text"},{"text":"Double","kind":"typeIdentifier","preciseIdentifier":"s:Sd"},{"text":") -> [","kind":"text"},{"preciseIdentifier":"c:objc(cs)CLLocation","kind":"typeIdentifier","text":"CLLocation"},{"kind":"text","text":"]?"}]},"doc://com.mapbox.navigation/documentation/MapboxDirections/ResponseOptions":{"type":"topic","title":"ResponseOptions","identifier":"doc:\/\/com.mapbox.navigation\/documentation\/MapboxDirections\/ResponseOptions","navigatorTitle":[{"text":"ResponseOptions","kind":"identifier"}],"url":"\/documentation\/mapboxdirections\/responseoptions","kind":"symbol","role":"symbol","abstract":[],"fragments":[{"kind":"keyword","text":"enum"},{"kind":"text","text":" "},{"text":"ResponseOptions","kind":"identifier"}]},"doc://com.mapbox.navigation/documentation/MapboxDirections/OfflineDownloaderCompletionHandler":{"role":"symbol","url":"\/documentation\/mapboxdirections\/offlinedownloadercompletionhandler","identifier":"doc:\/\/com.mapbox.navigation\/documentation\/MapboxDirections\/OfflineDownloaderCompletionHandler","type":"topic","abstract":[],"navigatorTitle":[{"kind":"identifier","text":"OfflineDownloaderCompletionHandler"}],"fragments":[{"kind":"keyword","text":"typealias"},{"kind":"text","text":" "},{"text":"OfflineDownloaderCompletionHandler","kind":"identifier"}],"title":"OfflineDownloaderCompletionHandler","kind":"symbol"},"doc://com.mapbox.navigation/documentation/MapboxDirections/DirectionsOptions":{"title":"DirectionsOptions","abstract":[{"type":"text","text":"Options for calculating results from the Mapbox Directions service."}],"url":"\/documentation\/mapboxdirections\/directionsoptions","identifier":"doc:\/\/com.mapbox.navigation\/documentation\/MapboxDirections\/DirectionsOptions","fragments":[{"kind":"keyword","text":"class"},{"text":" ","kind":"text"},{"text":"DirectionsOptions","kind":"identifier"}],"type":"topic","role":"symbol","navigatorTitle":[{"text":"DirectionsOptions","kind":"identifier"}],"kind":"symbol"},"https://docs.mapbox.com/vector-tiles/reference/mapbox-streets-v8/#road":{"titleInlineContent":[{"text":"Mapbox Streets","type":"text"},{"type":"text","text":" "},{"type":"text","text":"source"}],"identifier":"https:\/\/docs.mapbox.com\/vector-tiles\/reference\/mapbox-streets-v8\/#road","url":"https:\/\/docs.mapbox.com\/vector-tiles\/reference\/mapbox-streets-v8\/#road","title":"Mapbox Streets source","type":"link"},"doc://com.mapbox.navigation/documentation/MapboxDirections/Weight":{"title":"Weight","role":"symbol","fragments":[{"text":"enum","kind":"keyword"},{"kind":"text","text":" "},{"text":"Weight","kind":"identifier"}],"url":"\/documentation\/mapboxdirections\/weight","abstract":[{"type":"text","text":"A "},{"isActive":true,"identifier":"doc:\/\/com.mapbox.navigation\/documentation\/MapboxDirections\/Weight","type":"reference"},{"text":" enum represents the weight given to a specific ","type":"text"},{"identifier":"doc:\/\/com.mapbox.navigation\/documentation\/MapboxDirections\/Match","isActive":true,"type":"reference"},{"text":" by the Directions API. The default metric is a","type":"text"},{"type":"text","text":" "},{"type":"text","text":"compound index called “routability”, which is duration-based with additional penalties for less desirable maneuvers."}],"navigatorTitle":[{"kind":"identifier","text":"Weight"}],"kind":"symbol","type":"topic","identifier":"doc:\/\/com.mapbox.navigation\/documentation\/MapboxDirections\/Weight"},"doc://com.mapbox.navigation/documentation/MapboxDirections/DirectionsCredentials":{"type":"topic","title":"DirectionsCredentials","identifier":"doc:\/\/com.mapbox.navigation\/documentation\/MapboxDirections\/DirectionsCredentials","navigatorTitle":[{"text":"DirectionsCredentials","kind":"identifier"}],"url":"\/documentation\/mapboxdirections\/directionscredentials","kind":"symbol","role":"symbol","abstract":[],"fragments":[{"text":"typealias","kind":"keyword"},{"kind":"text","text":" "},{"kind":"identifier","text":"DirectionsCredentials"}],"deprecated":true},"doc://com.mapbox.navigation/documentation/MapboxDirections/Junction":{"kind":"symbol","identifier":"doc:\/\/com.mapbox.navigation\/documentation\/MapboxDirections\/Junction","role":"symbol","type":"topic","abstract":[{"type":"text","text":"Contains information about routing and passing junction along the route."}],"fragments":[{"kind":"keyword","text":"struct"},{"text":" ","kind":"text"},{"kind":"identifier","text":"Junction"}],"navigatorTitle":[{"text":"Junction","kind":"identifier"}],"url":"\/documentation\/mapboxdirections\/junction","title":"Junction"},"doc://com.mapbox.navigation/documentation/MapboxDirections/CustomValueOptionSet/customOptionsByRawValue":{"fragments":[{"text":"var","kind":"keyword"},{"kind":"text","text":" "},{"text":"customOptionsByRawValue","kind":"identifier"},{"kind":"text","text":": ["},{"kind":"typeIdentifier","preciseIdentifier":"s:SY8RawValueQa","text":"RawValue"},{"text":" : ","kind":"text"},{"kind":"typeIdentifier","preciseIdentifier":"s:16MapboxDirections20CustomValueOptionSetP0cD0Qa","text":"CustomValue"},{"text":"]","kind":"text"}],"role":"symbol","url":"\/documentation\/mapboxdirections\/customvalueoptionset\/customoptionsbyrawvalue","abstract":[{"text":"Provides a text value description for user-provided options.","type":"text"}],"identifier":"doc:\/\/com.mapbox.navigation\/documentation\/MapboxDirections\/CustomValueOptionSet\/customOptionsByRawValue","type":"topic","title":"customOptionsByRawValue","kind":"symbol","required":true},"doc://com.mapbox.navigation/documentation/MapboxDirections/IsochroneOptions":{"url":"\/documentation\/mapboxdirections\/isochroneoptions","navigatorTitle":[{"text":"IsochroneOptions","kind":"identifier"}],"title":"IsochroneOptions","role":"symbol","fragments":[{"text":"struct","kind":"keyword"},{"text":" ","kind":"text"},{"text":"IsochroneOptions","kind":"identifier"}],"type":"topic","abstract":[{"type":"text","text":"Options for calculating contours from the Mapbox Isochrone service."}],"identifier":"doc:\/\/com.mapbox.navigation\/documentation\/MapboxDirections\/IsochroneOptions","kind":"symbol"},"doc://com.mapbox.navigation/documentation/MapboxDirections/TollCollection":{"kind":"symbol","identifier":"doc:\/\/com.mapbox.navigation\/documentation\/MapboxDirections\/TollCollection","role":"symbol","type":"topic","abstract":[{"type":"codeVoice","code":"TollCollection"},{"text":" describes corresponding object on the route.","type":"text"}],"fragments":[{"kind":"keyword","text":"struct"},{"text":" ","kind":"text"},{"kind":"identifier","text":"TollCollection"}],"navigatorTitle":[{"kind":"identifier","text":"TollCollection"}],"url":"\/documentation\/mapboxdirections\/tollcollection","title":"TollCollection"},"doc://com.mapbox.navigation/documentation/MapboxDirections/Matrix":{"title":"Matrix","abstract":[{"text":"Computes distances and durations between origin-destination pairs, and returns the resulting distances in meters and","type":"text"},{"text":" ","type":"text"},{"type":"text","text":"durations in seconds."}],"url":"\/documentation\/mapboxdirections\/matrix","identifier":"doc:\/\/com.mapbox.navigation\/documentation\/MapboxDirections\/Matrix","fragments":[{"kind":"keyword","text":"class"},{"text":" ","kind":"text"},{"text":"Matrix","kind":"identifier"}],"type":"topic","role":"symbol","navigatorTitle":[{"kind":"identifier","text":"Matrix"}],"kind":"symbol"},"doc://com.mapbox.navigation/documentation/MapboxDirections/RouteRefreshResponse":{"navigatorTitle":[{"kind":"identifier","text":"RouteRefreshResponse"}],"kind":"symbol","identifier":"doc:\/\/com.mapbox.navigation\/documentation\/MapboxDirections\/RouteRefreshResponse","title":"RouteRefreshResponse","type":"topic","abstract":[{"type":"text","text":"A Directions Refresh API response."}],"role":"symbol","fragments":[{"kind":"keyword","text":"struct"},{"kind":"text","text":" "},{"kind":"identifier","text":"RouteRefreshResponse"}],"url":"\/documentation\/mapboxdirections\/routerefreshresponse"},"doc://com.mapbox.navigation/documentation/MapboxDirections/RouteShapeResolution":{"abstract":[{"text":"A ","type":"text"},{"identifier":"doc:\/\/com.mapbox.navigation\/documentation\/MapboxDirections\/RouteShapeResolution","isActive":true,"type":"reference"},{"type":"text","text":" indicates the level of detail in a route’s shape, or whether the shape is present at all."}],"identifier":"doc:\/\/com.mapbox.navigation\/documentation\/MapboxDirections\/RouteShapeResolution","url":"\/documentation\/mapboxdirections\/routeshaperesolution","type":"topic","title":"RouteShapeResolution","role":"symbol","fragments":[{"kind":"keyword","text":"enum"},{"text":" ","kind":"text"},{"kind":"identifier","text":"RouteShapeResolution"}],"kind":"symbol","navigatorTitle":[{"kind":"identifier","text":"RouteShapeResolution"}]},"doc://com.mapbox.navigation/documentation/MapboxDirections/TollPrice":{"identifier":"doc:\/\/com.mapbox.navigation\/documentation\/MapboxDirections\/TollPrice","title":"TollPrice","type":"topic","navigatorTitle":[{"kind":"identifier","text":"TollPrice"}],"url":"\/documentation\/mapboxdirections\/tollprice","kind":"symbol","role":"symbol","abstract":[{"text":"Toll cost information for the ","type":"text"},{"isActive":true,"type":"reference","identifier":"doc:\/\/com.mapbox.navigation\/documentation\/MapboxDirections\/Route"},{"type":"text","text":"."}],"fragments":[{"text":"struct","kind":"keyword"},{"text":" ","kind":"text"},{"text":"TollPrice","kind":"identifier"}]},"doc://com.mapbox.navigation/documentation/MapboxDirections/NumericCongestionLevel":{"type":"topic","title":"NumericCongestionLevel","identifier":"doc:\/\/com.mapbox.navigation\/documentation\/MapboxDirections\/NumericCongestionLevel","navigatorTitle":[{"text":"NumericCongestionLevel","kind":"identifier"}],"url":"\/documentation\/mapboxdirections\/numericcongestionlevel","kind":"symbol","role":"symbol","abstract":[{"code":"NumericCongestionLevel","type":"codeVoice"},{"type":"text","text":" is the level of traffic congestion along a road segment in numeric form, from 0-100. A"},{"text":" ","type":"text"},{"type":"text","text":"value of 0 indicates no congestion, a value of 100 indicates maximum congestion."}],"fragments":[{"kind":"keyword","text":"typealias"},{"kind":"text","text":" "},{"kind":"identifier","text":"NumericCongestionLevel"}]},"doc://com.mapbox.navigation/documentation/MapboxDirections/Swift":{"role":"collection","identifier":"doc:\/\/com.mapbox.navigation\/documentation\/MapboxDirections\/Swift","abstract":[],"kind":"symbol","url":"\/documentation\/mapboxdirections\/swift","type":"topic","title":"Swift"},"doc://com.mapbox.navigation/documentation/MapboxDirections/LocationSpeed":{"abstract":[{"text":"The velocity (measured in meters per second) at which the device is moving.","type":"text"}],"role":"symbol","identifier":"doc:\/\/com.mapbox.navigation\/documentation\/MapboxDirections\/LocationSpeed","type":"topic","title":"LocationSpeed","fragments":[{"text":"typealias","kind":"keyword"},{"text":" ","kind":"text"},{"text":"LocationSpeed","kind":"identifier"}],"navigatorTitle":[{"text":"LocationSpeed","kind":"identifier"}],"kind":"symbol","url":"\/documentation\/mapboxdirections\/locationspeed"},"doc://com.mapbox.navigation/documentation/MapboxDirections/OfflineDownloaderProgressHandler":{"identifier":"doc:\/\/com.mapbox.navigation\/documentation\/MapboxDirections\/OfflineDownloaderProgressHandler","abstract":[],"fragments":[{"text":"typealias","kind":"keyword"},{"text":" ","kind":"text"},{"kind":"identifier","text":"OfflineDownloaderProgressHandler"}],"role":"symbol","title":"OfflineDownloaderProgressHandler","type":"topic","kind":"symbol","url":"\/documentation\/mapboxdirections\/offlinedownloaderprogresshandler","navigatorTitle":[{"text":"OfflineDownloaderProgressHandler","kind":"identifier"}]},"doc://com.mapbox.navigation/documentation/MapboxDirections/RouteLegRefreshSource":{"identifier":"doc:\/\/com.mapbox.navigation\/documentation\/MapboxDirections\/RouteLegRefreshSource","title":"RouteLegRefreshSource","type":"topic","navigatorTitle":[{"text":"RouteLegRefreshSource","kind":"identifier"}],"url":"\/documentation\/mapboxdirections\/routelegrefreshsource","kind":"symbol","role":"symbol","abstract":[{"type":"text","text":"A skeletal route leg containing infromation to refresh "},{"identifier":"doc:\/\/com.mapbox.navigation\/documentation\/MapboxDirections\/RouteLeg","isActive":true,"type":"reference"},{"type":"text","text":" object attributes."}],"fragments":[{"text":"protocol","kind":"keyword"},{"text":" ","kind":"text"},{"text":"RouteLegRefreshSource","kind":"identifier"}]},"doc://com.mapbox.navigation/documentation/MapboxDirections/MapMatchingResponse":{"role":"symbol","fragments":[{"kind":"keyword","text":"struct"},{"text":" ","kind":"text"},{"text":"MapMatchingResponse","kind":"identifier"}],"navigatorTitle":[{"text":"MapMatchingResponse","kind":"identifier"}],"identifier":"doc:\/\/com.mapbox.navigation\/documentation\/MapboxDirections\/MapMatchingResponse","abstract":[{"type":"text","text":"A "},{"identifier":"doc:\/\/com.mapbox.navigation\/documentation\/MapboxDirections\/MapMatchingResponse","type":"reference","isActive":true},{"text":" object is a structure that corresponds to a map matching response returned by the Mapbox","type":"text"},{"type":"text","text":" "},{"type":"text","text":"Map Matching API."}],"kind":"symbol","url":"\/documentation\/mapboxdirections\/mapmatchingresponse","title":"MapMatchingResponse","type":"topic"},"doc://com.mapbox.navigation/documentation/MapboxDirections/DirectionsCodingError":{"type":"topic","title":"DirectionsCodingError","identifier":"doc:\/\/com.mapbox.navigation\/documentation\/MapboxDirections\/DirectionsCodingError","navigatorTitle":[{"kind":"identifier","text":"DirectionsCodingError"}],"url":"\/documentation\/mapboxdirections\/directionscodingerror","kind":"symbol","role":"symbol","abstract":[{"type":"text","text":"An error that occurs when encoding or decoding a type defined by the MapboxDirections framework."}],"fragments":[{"text":"enum","kind":"keyword"},{"text":" ","kind":"text"},{"kind":"identifier","text":"DirectionsCodingError"}]},"doc://com.mapbox.navigation/documentation/MapboxDirections/GeometryError":{"identifier":"doc:\/\/com.mapbox.navigation\/documentation\/MapboxDirections\/GeometryError","title":"GeometryError","type":"topic","navigatorTitle":[{"text":"GeometryError","kind":"identifier"}],"url":"\/documentation\/mapboxdirections\/geometryerror","kind":"symbol","role":"symbol","abstract":[],"fragments":[{"kind":"keyword","text":"enum"},{"text":" ","kind":"text"},{"text":"GeometryError","kind":"identifier"}]},"doc://com.mapbox.navigation/documentation/MapboxDirections/DirectionsCodingKey":{"url":"\/documentation\/mapboxdirections\/directionscodingkey","identifier":"doc:\/\/com.mapbox.navigation\/documentation\/MapboxDirections\/DirectionsCodingKey","type":"topic","title":"DirectionsCodingKey","abstract":[],"role":"symbol","fragments":[{"kind":"keyword","text":"struct"},{"text":" ","kind":"text"},{"text":"DirectionsCodingKey","kind":"identifier"}],"kind":"symbol","navigatorTitle":[{"kind":"identifier","text":"DirectionsCodingKey"}]},"doc://com.mapbox.navigation/documentation/MapboxDirections/TrafficTendency":{"abstract":[{"type":"text","text":":nodoc:"},{"type":"text","text":" "},{"type":"text","text":"The tendency value conveys the changing state of traffic congestion (increasing, decreasing, constant etc)."}],"fragments":[{"kind":"keyword","text":"enum"},{"kind":"text","text":" "},{"kind":"identifier","text":"TrafficTendency"}],"navigatorTitle":[{"text":"TrafficTendency","kind":"identifier"}],"role":"symbol","title":"TrafficTendency","kind":"symbol","type":"topic","identifier":"doc:\/\/com.mapbox.navigation\/documentation\/MapboxDirections\/TrafficTendency","url":"\/documentation\/mapboxdirections\/traffictendency"},"doc://com.mapbox.navigation/documentation/MapboxDirections/AttributeOptions":{"identifier":"doc:\/\/com.mapbox.navigation\/documentation\/MapboxDirections\/AttributeOptions","navigatorTitle":[{"text":"AttributeOptions","kind":"identifier"}],"role":"symbol","type":"topic","abstract":[{"type":"text","text":"Attributes are metadata information for a route leg."}],"fragments":[{"text":"struct","kind":"keyword"},{"text":" ","kind":"text"},{"text":"AttributeOptions","kind":"identifier"}],"url":"\/documentation\/mapboxdirections\/attributeoptions","kind":"symbol","title":"AttributeOptions"},"doc://com.mapbox.navigation/documentation/MapboxDirections/DirectionsPriority":{"role":"symbol","fragments":[{"text":"struct","kind":"keyword"},{"text":" ","kind":"text"},{"kind":"identifier","text":"DirectionsPriority"}],"navigatorTitle":[{"text":"DirectionsPriority","kind":"identifier"}],"identifier":"doc:\/\/com.mapbox.navigation\/documentation\/MapboxDirections\/DirectionsPriority","url":"\/documentation\/mapboxdirections\/directionspriority","title":"DirectionsPriority","type":"topic","abstract":[{"text":"A number that influences whether a route should prefer or avoid roadways or pathways of a given type.","type":"text"}],"kind":"symbol"},"doc://com.mapbox.navigation/documentation/MapboxDirections/decodeLevels(_:)":{"type":"topic","title":"decodeLevels(_:)","identifier":"doc:\/\/com.mapbox.navigation\/documentation\/MapboxDirections\/decodeLevels(_:)","url":"\/documentation\/mapboxdirections\/decodelevels(_:)","kind":"symbol","role":"symbol","abstract":[{"text":"This function decodes a ","type":"text"},{"type":"codeVoice","code":"String"},{"type":"text","text":" to an "},{"type":"codeVoice","code":"[UInt32]"}],"fragments":[{"kind":"keyword","text":"func"},{"kind":"text","text":" "},{"text":"decodeLevels","kind":"identifier"},{"text":"(","kind":"text"},{"text":"String","kind":"typeIdentifier","preciseIdentifier":"s:SS"},{"text":") -> [","kind":"text"},{"text":"UInt32","preciseIdentifier":"s:s6UInt32V","kind":"typeIdentifier"},{"text":"]?","kind":"text"}]}}}